sparkdh/__init__.py
sparkdh/dataframe_column_functions.py
sparkdh/dataframe_creation.py
sparkdh-0.0.1.dist-info/LICENSE
sparkdh-0.0.1.dist-info/METADATA
sparkdh-0.0.1.dist-info/WHEEL
sparkdh-0.0.1.dist-info/top_level.txt
sparkdh-0.0.1.dist-info/RECORD
