Metadata-Version: 2.1
Name: sparkdh
Version: 0.0.1
Summary: UNKNOWN
Home-page: https://github.com/mmutiso/spark-dh
Author: Matthew Mutiso
Author-email: UNKNOWN
License: Apache License 2.0
Keywords: spark pyspark dataframe hdfs hadoop data-science
Platform: UNKNOWN
Requires-Dist: pyspark
